JanusReader/__init__.py
JanusReader/__main__.py
JanusReader/exceptions.py
JanusReader/py.typed
JanusReader/vicar_head.py
janusreader-0.13.0.dist-info/METADATA
janusreader-0.13.0.dist-info/WHEEL
janusreader-0.13.0.dist-info/entry_points.txt
janusreader-0.13.0.dist-info/top_level.txt
janusreader-0.13.0.dist-info/RECORD
