Metadata-Version: 2.4
Name: JanusReader
Version: 0.13.0
Summary: Python Reader for the data from JANUS instrument suite on-board the ESA mission JUICE
Author-email: Romolo Politi <Romolo.Politi@inaf.it>, Luca Penasa <Luca.Penasa@inaf.it>
Maintainer-email: Romolo Politi <Romolo.Politi@inaf.it>, Luca Penasa <Luca.Penasa@inaf.it>
License: GNU GPL ver3
Project-URL: Repository, https://github.com/JANUS-JUICE/janusReader
Classifier: License :: OSI Approved :: GNU General Public License v3 (GPLv3)
Requires-Dist: numpy
Requires-Dist: rich
Requires-Dist: rich_click
Requires-Dist: importlib-metadata; python_version > "3.10"
Provides-Extra: docs
Requires-Dist: sphinx; extra == "docs"
